google_drive_sync/__init__.py
google_drive_sync/google_drive_sync.py
google_drive_sync-0.1.0.dist-info/top_level.txt
google_drive_sync-0.1.0.dist-info/METADATA
google_drive_sync-0.1.0.dist-info/DESCRIPTION.rst
google_drive_sync-0.1.0.dist-info/WHEEL
google_drive_sync-0.1.0.dist-info/RECORD
google_drive_sync-0.1.0.dist-info/metadata.json
