Metadata-Version: 2.0
Name: google-drive-sync
Version: 0.1.0
Summary: Sync The current folder and all its subfolders to Google Drive
Home-page: https://github.com/maxc0c0s/google_drive_sync
Author: Sebastien Delisle
Author-email: seb0del@gmail.com
License: BSD
Keywords: google_drive_sync
Platform: UNKNOWN
Classifier: Development Status :: 2 - Pre-Alpha
Classifier: Intended Audience :: Developers
Classifier: License :: OSI Approved :: BSD License
Classifier: Natural Language :: English
Classifier: Programming Language :: Python :: 2
Classifier: Programming Language :: Python :: 2.6
Classifier: Programming Language :: Python :: 2.7
Classifier: Programming Language :: Python :: 3
Classifier: Programming Language :: Python :: 3.3
Classifier: Programming Language :: Python :: 3.4
